Flickr/__init__.py
Flickr/__main__.py
Flickr/model/flickr.py
Flickr_nqcuong96-1.1.2.dist-info/METADATA
Flickr_nqcuong96-1.1.2.dist-info/WHEEL
Flickr_nqcuong96-1.1.2.dist-info/entry_points.txt
Flickr_nqcuong96-1.1.2.dist-info/top_level.txt
Flickr_nqcuong96-1.1.2.dist-info/RECORD
