Metadata-Version: 2.1
Name: Flickr-nqcuong96
Version: 1.1.2
Summary: A tool to mirror Flickr photo
Home-page: https://github.com/intek-training-jsc/flickr-mirroring-nqcuong96
Author: nqcuong
Author-email: cuong.nguyen@f4.intek.edu.vn
License: MIT
Platform: UNKNOWN
Classifier: License :: OSI Approved :: MIT License
Classifier: Programming Language :: Python :: 3
Classifier: Programming Language :: Python :: 3.7
Requires-Dist: langdetect
Requires-Dist: iso-639
Requires-Dist: iso3166
Requires-Dist: requests
